{
  "posts": [
    {
      "id": 2,
      "title": "2 Posty 2 Furious 4 me",
      "datetime": "August 20,2023 6:35:24 PM",
      "body": "Lorem ipsum dolor sit amet consectetur adipisicing elit. Quis consequatur expedita, assumenda similique non optio! Modi nesciunt excepturi corrupti atque blanditiis quo nobis, non optio quae possimus illum exercitationem ipsa!"
    },
    {
      "id": 5,
      "title": "21 Savage",
      "datetime": "August 26,2023 4:42:41 AM",
      "body": "He think he the battery...\nWe call him Elon Musk."
    },
    {
      "id": 7,
      "title": "The Weeknd",
      "datetime": "August 26,2023 4:41:04 AM",
      "body": "I know you know this ... and you know mine.\nThe ones that love me I ... tend to leave behind."
    },
    {
      "id": 8,
      "title": "Drake 2 Electric Boogaloo",
      "datetime": "August 26,2023 4:44:20 AM",
      "body": "All my capitals like I got the caps lock on\n\n-- Drake -- Jodeci Freestyle."
    },
    {
      "id": 9,
      "title": "The Good, The Bad, The Ugly",
      "datetime": "August 24,2023 3:29:47 AM",
      "body": "The Good, The Bad, The Ugly"
    },
    {
      "id": 10,
      "title": "Bitch I'm Stylish",
      "datetime": "August 26,2023 4:38:27 AM",
      "body": "Glock T shirt Billie Eilish"
    },
    {
      "id": 11,
      "title": "New Bars just dropped.",
      "datetime": "August 26,2023 4:45:56 AM",
      "body": "First things first .... \n\nRest in Piece Uncle Phil."
    }
  ]
}